<?xml version="1.0" encoding="utf-8" ?>
<dwsync>
<file name="伏打電池.gif" server="203.72.64.251//chen/" local="128816599340000000" remote="129119011800000000" />
<file name="電池3.jpg" server="203.72.64.251//chen/" local="128816599380000000" remote="129119011800000000" />
<file name="水銀電池.jpg" server="203.72.64.251//chen/" local="128816599340000000" remote="129119011800000000" />
<file name="鉛蓄電池.jpg" server="203.72.64.251//chen/" local="128816599360000000" remote="129119011800000000" />
<file name="生物電池.jpg" server="203.72.64.251//chen/" local="128816599360000000" remote="129119011800000000" />
<file name="燃料電池.jpg" server="203.72.64.251//chen/" local="128816599360000000" remote="129119012400000000" />
<file name="背景.jpg" server="203.72.64.251//chen/" local="128816599360000000" remote="129119012400000000" />
<file name="電池.jpg" server="203.72.64.251//chen/" local="128816599380000000" remote="129119012400000000" />
<file name="電池1.jpg" server="203.72.64.251//chen/" local="128816599380000000" remote="129119012400000000" />
<file name="電池全球分布.jpg" server="203.72.64.251//chen/" local="128816599380000000" remote="129119012400000000" />
</dwsync>